README.rst
setup.py
placebo/__init__.py
placebo/base.py
placebo/request.py
placebo/backends/__init__.py
placebo/backends/httmockbackend.py
placebo/backends/httprettybackend.py
placebo/utils/__init__.py
placebo/utils/datautils.py
placebo/utils/importutils.py
python_placebo.egg-info/PKG-INFO
python_placebo.egg-info/SOURCES.txt
python_placebo.egg-info/dependency_links.txt
python_placebo.egg-info/not-zip-safe
python_placebo.egg-info/top_level.txt
tests/__init__.py
tests/placebo_tests.py
tests/utils.py